votify/__init__.py
votify/__main__.py
votify/cli.py
votify/config_file.py
votify/constants.py
votify/custom_logger_formatter.py
votify/device_flow.py
votify/downloader.py
votify/downloader_audio.py
votify/downloader_episode.py
votify/downloader_episode_video.py
votify/downloader_music_video.py
votify/downloader_song.py
votify/downloader_video.py
votify/enums.py
votify/models.py
votify/spotify_api.py
votify/totp.py
votify/utils.py
votify-1.5.9.dist-info/entry_points.txt
votify-1.5.9.dist-info/licenses/LICENSE
votify-1.5.9.dist-info/WHEEL
votify-1.5.9.dist-info/METADATA
votify-1.5.9.dist-info/RECORD
