Metadata-Version: 2.4
Name: votify
Version: 1.5.9
Summary: A command-line app for downloading songs, podcasts and videos from Spotify.
Author: glomatico
Requires-Python: >=3.10
License-File: LICENSE
Requires-Dist: click
Requires-Dist: colorama
Requires-Dist: inquirerpy
Requires-Dist: mutagen
Requires-Dist: pillow
Requires-Dist: protobuf
Requires-Dist: pybase62
Requires-Dist: pycryptodome
Requires-Dist: pywidevine
Requires-Dist: yt-dlp
Project-URL: repository, https://github.com/glomatico/votify
